AUTHORS
LICENSE
MANIFEST.in
README.rst
setup.py
django_templated_email_db.egg-info/PKG-INFO
django_templated_email_db.egg-info/SOURCES.txt
django_templated_email_db.egg-info/dependency_links.txt
django_templated_email_db.egg-info/top_level.txt
templated_email/__init__.py
templated_email/models.py
templated_email/tests.py
templated_email/utils.py
templated_email/backends/__init__.py
templated_email/backends/mailchimp_sts.py
templated_email/backends/postageapp_backend.py
templated_email/backends/vanilla_django.py
templated_email/backends/database/__init__.py
templated_email/backends/database/admin.py
templated_email/backends/database/backend.py
templated_email/backends/database/fields.py
templated_email/backends/database/models.py
templated_email/backends/database/widgets.py
templated_email/backends/database/locale/ru/LC_MESSAGES/django.mo
templated_email/backends/database/locale/ru/LC_MESSAGES/django.po
templated_email/backends/database/static/codemirror/lib/codemirror.css
templated_email/backends/database/static/codemirror/lib/codemirror.js
templated_email/backends/database/static/codemirror/mode/meta.js
templated_email/backends/database/static/codemirror/mode/css/css.js
templated_email/backends/database/static/codemirror/mode/css/index.html
templated_email/backends/database/static/codemirror/mode/css/scss.html
templated_email/backends/database/static/codemirror/mode/css/scss_test.js
templated_email/backends/database/static/codemirror/mode/css/test.js
templated_email/backends/database/static/codemirror/mode/htmlembedded/htmlembedded.js
templated_email/backends/database/static/codemirror/mode/htmlembedded/index.html
templated_email/backends/database/static/codemirror/mode/htmlmixed/htmlmixed.js
templated_email/backends/database/static/codemirror/mode/htmlmixed/index.html